django_regex_redirects-0.7.0.dist-info/licenses/LICENSE
regex_redirects/__init__.py
regex_redirects/actions.py
regex_redirects/admin.py
regex_redirects/apps.py
regex_redirects/middleware.py
regex_redirects/models.py
regex_redirects/tests.py
regex_redirects/migrations/0001_initial.py
regex_redirects/migrations/0002_auto_20151217_1938.py
regex_redirects/migrations/0004_auto_20170512_1349.py
regex_redirects/migrations/0005_auto_20210425_1321.py
regex_redirects/migrations/__init__.py
django_regex_redirects-0.7.0.dist-info/METADATA
django_regex_redirects-0.7.0.dist-info/WHEEL
django_regex_redirects-0.7.0.dist-info/top_level.txt
django_regex_redirects-0.7.0.dist-info/RECORD
