Metadata-Version: 2.4
Name: django-regex-redirects
Version: 0.7.0
Summary: Django redirects, with regular expressions
Author-email: Alex de Landgraaf <alex@maykinmedia.nl>
License: Copyright (c) 2013, Maykin Media
Project-URL: Homepage, https://github.com/maykinmedia/django-regex-redirects
Project-URL: Bug Tracker, https://github.com/maykinmedia/django-regex-redirects/issues
Project-URL: Source Code, https://github.com/maykinmedia/django-regex-redirects
Keywords: Django,regex
Classifier: Development Status :: 5 - Production/Stable
Classifier: Framework :: Django
Classifier: Framework :: Django :: 3.2
Classifier: Framework :: Django :: 4.2
Classifier: Framework :: Django :: 5.2
Classifier: Intended Audience :: Developers
Classifier: Operating System :: Unix
Classifier: Operating System :: MacOS
Classifier: Operating System :: Microsoft :: Windows
Classifier: Programming Language :: Python :: 3.8
Classifier: Programming Language :: Python :: 3.9
Classifier: Programming Language :: Python :: 3.10
Classifier: Programming Language :: Python :: 3.11
Classifier: Programming Language :: Python :: 3.12
Classifier: Topic :: Software Development :: Libraries :: Python Modules
Requires-Python: >=3.8
License-File: LICENSE
Requires-Dist: django>=3.2
Provides-Extra: tests
Requires-Dist: tox; extra == "tests"
Requires-Dist: isort; extra == "tests"
Requires-Dist: black; extra == "tests"
Requires-Dist: flake8; extra == "tests"
Dynamic: license-file
